XBoss/XB.py
XBoss/__init__.py
XBoss-0.0.3.dist-info/METADATA
XBoss-0.0.3.dist-info/WHEEL
XBoss-0.0.3.dist-info/top_level.txt
XBoss-0.0.3.dist-info/RECORD
